iotile_transport_socket_lib/__init__.py
iotile_transport_socket_lib/generic/__init__.py
iotile_transport_socket_lib/generic/abstract_socket_implementation.py
iotile_transport_socket_lib/generic/device_adapter.py
iotile_transport_socket_lib/generic/device_server.py
iotile_transport_socket_lib/generic/errors.py
iotile_transport_socket_lib/generic/packing.py
iotile_transport_socket_lib/generic/socket_client.py
iotile_transport_socket_lib/generic/socket_server.py
iotile_transport_socket_lib/protocol/__init__.py
iotile_transport_socket_lib/protocol/commands.py
iotile_transport_socket_lib/protocol/messages.py
iotile_transport_socket_lib/protocol/notifications.py
iotile_transport_socket_lib/protocol/operations.py
iotile_transport_socket_lib/tcp_socket/__init__.py
iotile_transport_socket_lib/tcp_socket/tcpsocket_adapter.py
iotile_transport_socket_lib/tcp_socket/tcpsocket_implementation.py
iotile_transport_socket_lib/tcp_socket/tcpsocket_server.py
iotile_transport_socket_lib/unix_socket/__init__.py
iotile_transport_socket_lib/unix_socket/unixsocket_adapter.py
iotile_transport_socket_lib/unix_socket/unixsocket_implementation.py
iotile_transport_socket_lib/unix_socket/unixsocket_server.py
iotile_transport_socket_lib-1.1.0.dist-info/LICENSE.md
iotile_transport_socket_lib-1.1.0.dist-info/METADATA
iotile_transport_socket_lib-1.1.0.dist-info/WHEEL
iotile_transport_socket_lib-1.1.0.dist-info/entry_points.txt
iotile_transport_socket_lib-1.1.0.dist-info/top_level.txt
iotile_transport_socket_lib-1.1.0.dist-info/RECORD
